chatgpt_mixin/__init__.py
chatgpt_mixin/__main__.py
chatgpt_mixin/chatgpt_browser.py
chatgpt_mixin/chatgpt_openai.py
chatgpt_mixin/mixinbot.py
chatgpt_mixin/test.py
chatgpt_mixin-0.1.8.dist-info/LICENSE
chatgpt_mixin-0.1.8.dist-info/METADATA
chatgpt_mixin-0.1.8.dist-info/WHEEL
chatgpt_mixin-0.1.8.dist-info/entry_points.txt
chatgpt_mixin-0.1.8.dist-info/top_level.txt
chatgpt_mixin-0.1.8.dist-info/RECORD
