Metadata-Version: 2.1
Name: chatgpt-mixin
Version: 0.1.8
Summary: ChatGPT Bot For Mixin
Home-page: https://github.com/learnforpractice/chatgpt-mixin
Author: learnforpractice
License: Apache 2.0
License-File: LICENSE
Requires-Dist: pyyaml
Requires-Dist: mixin-python
Requires-Dist: tiktoken
Requires-Dist: openai (>=0.27.0)
Provides-Extra: browser
Requires-Dist: playwright ; extra == 'browser'
Requires-Dist: cf-clearance ; extra == 'browser'
